{"changes":{"crates/vespertide-macro/Cargo.toml":"Patch","crates/vespertide-planner/Cargo.toml":"Patch","crates/vespertide-config/Cargo.toml":"Patch","crates/vespertide-query/Cargo.toml":"Patch","crates/vespertide-loader/Cargo.toml":"Patch","crates/vespertide/Cargo.toml":"Patch","crates/vespertide-exporter/Cargo.toml":"Patch","crates/vespertide-cli/Cargo.toml":"Patch","crates/vespertide-core/Cargo.toml":"Patch","crates/vespertide-naming/Cargo.toml":"Patch"},"note":"Fix derive","date":"2026-02-03T11:39:47.686761200Z"}